MANIFEST.in
README.md
setup.py
contrib/nuklear/gl3w.h
contrib/nuklear/glcorearb.h
contrib/nuklear/main.c
contrib/nuklear/nuklear.h
contrib/nuklear/nuklearGLFWOpenGL2.c
contrib/nuklear/nuklearGLFWOpenGL3.c
contrib/nuklear/nuklearWrappers.h
contrib/nuklear/nuklear_glfw_gl2.h
contrib/nuklear/nuklear_glfw_gl3.h
pyNuklear.egg-info/PKG-INFO
pyNuklear.egg-info/SOURCES.txt
pyNuklear.egg-info/dependency_links.txt
pyNuklear.egg-info/requires.txt
pyNuklear.egg-info/top_level.txt
src/pynuklear/__init__.py
src/pynuklear/glfw3.py
src/pynuklear/nuklear.py
src/pynuklear/demo/__init__.py
src/pynuklear/demo/overview.py
src/pynuklear/demo/glfw_opengl3/__init__.py
src/pynuklear/demo/glfw_opengl3/demo.py
src/pynuklear/demo/glfw_opengl3/demoTriangle.py
src/pynuklear/demo/glfw_opengl3/triangle.frag
src/pynuklear/demo/glfw_opengl3/triangle.vert